respace/__init__.py
respace/_typing.py
respace/parameters.py
respace/py.typed
respace/result.py
respace/utils.py
respace-0.1.1.dist-info/LICENSE
respace-0.1.1.dist-info/WHEEL
respace-0.1.1.dist-info/METADATA
respace-0.1.1.dist-info/RECORD
