Metadata-Version: 2.1
Name: respace
Version: 0.1.1
Summary: ReSpace
Home-page: https://github.com/TLouf/respace
License: MIT
Author: Thomas Louf
Author-email: tlouf+pro@pm.me
Requires-Python: >=3.8,<3.12
Classifier: Development Status :: 1 - Planning
Classifier: License :: OSI Approved :: MIT License
Classifier: Programming Language :: Python :: 3
Classifier: Programming Language :: Python :: 3.8
Classifier: Programming Language :: Python :: 3.9
Classifier: Programming Language :: Python :: 3.10
Classifier: Programming Language :: Python :: 3.11
Requires-Dist: xarray (>=2023.01.0)
Project-URL: Changelog, https://github.com/TLouf/respace/releases
Project-URL: Documentation, https://respace.readthedocs.io
Project-URL: Repository, https://github.com/TLouf/respace
